baselooper/__init__.py
baselooper/looper.py
baselooper/module.py
baselooper/run.py
baselooper/state.py
baselooper/utils.py
baselooper-0.0.2.dist-info/LICENSE
baselooper-0.0.2.dist-info/METADATA
baselooper-0.0.2.dist-info/WHEEL
baselooper-0.0.2.dist-info/entry_points.txt
baselooper-0.0.2.dist-info/top_level.txt
baselooper-0.0.2.dist-info/RECORD
